{
  "packageId": "io.github.jimmylefrancois.twa",
  "host": "jimmylefrancois.github.io",
  "name": "Do Ré Mi Challenge",
  "launcherName": "DoReMi",
  "display": "standalone",
  "themeColor": "#667EEA",
  "themeColorDark": "#000000",
  "navigationColor": "#000000",
  "navigationColorDark": "#000000",
  "navigationDividerColor": "#000000",
  "navigationDividerColorDark": "#000000",
  "backgroundColor": "#FFFFFF",
  "enableNotifications": true,
  "startUrl": "/Do-Re-Mi-Challenge/index.html",
  "iconUrl": "https://jimmylefrancois.github.io/Do-Re-Mi-Challenge/icons/icon-512.png",
  "maskableIconUrl": "https://jimmylefrancois.github.io/Do-Re-Mi-Challenge/icons/icon-512-maskable.png",
  "splashScreenFadeOutDuration": 300,
  "signingKey": {
    "path": "/workspaces/Do-Re-Mi-Challenge/android-twa/android.keystore",
    "alias": "doremichallenge"
  },
  "appVersionName": "1",
  "appVersionCode": 1,
  "shortcuts": [],
  "generatorApp": "bubblewrap-cli",
  "webManifestUrl": "https://jimmylefrancois.github.io/Do-Re-Mi-Challenge/manifest.json",
  "fallbackType": "customtabs",
  "features": {},
  "alphaDependencies": {
    "enabled": false
  },
  "enableSiteSettingsShortcut": true,
  "isChromeOSOnly": false,
  "isMetaQuest": false,
  "fullScopeUrl": "https://jimmylefrancois.github.io/Do-Re-Mi-Challenge/",
  "minSdkVersion": 21,
  "orientation": "portrait",
  "fingerprints": [],
  "additionalTrustedOrigins": [],
  "retainedBundles": [],
  "protocolHandlers": [],
  "fileHandlers": [],
  "launchHandlerClientMode": "",
  "displayOverride": [],
  "appVersion": "1"
}